pelion_sagemaker_controller/__init__.py
pelion_sagemaker_controller/pelion_sagemaker_controller.py
pelion_sagemaker_controller-0.1.5.dist-info/METADATA
pelion_sagemaker_controller-0.1.5.dist-info/WHEEL
pelion_sagemaker_controller-0.1.5.dist-info/top_level.txt
pelion_sagemaker_controller-0.1.5.dist-info/RECORD
