Metadata-Version: 2.1
Name: pelion-sagemaker-controller
Version: 0.1.5
Summary: AWS Sagemaker Controller notebook/client API for Pelion Edge Gateways
Home-page: https://github.com/DougAnsonAtARM/pelion-sagemaker-controller
Author: Doug Anson
Author-email: Doug.Anson@pelion.com
License: Apache 2.0
Platform: UNKNOWN
Classifier: Development Status :: 3 - Alpha
Classifier: Intended Audience :: Developers
Classifier: License :: OSI Approved :: Apache Software License
Classifier: Programming Language :: Python :: 3.6
Classifier: Programming Language :: Python :: 3.7
Classifier: Programming Language :: Python
Classifier: Topic :: Internet
Requires-Python: >=2.7.10, !=3.0.*, !=3.1.*, !=3.2.*, !=3.3.*, !=3.4.0, !=3.4.1, !=3.4.2, <4
Requires-Dist: requests (>=2.24.0)
Requires-Dist: uuid (>=1.30)
